fairscoring/__init__.py
fairscoring/utils.py
fairscoring/metrics/__init__.py
fairscoring/metrics/base.py
fairscoring/metrics/calibration.py
fairscoring/metrics/integral.py
fairscoring/metrics/roc.py
fairscoring/plots/__init__.py
fairscoring/plots/_calibration.py
fairscoring/plots/_integral.py
fairscoring/plots/_utils.py
fairscoring/plots/colors.py
fair_scoring-0.2.1.dist-info/LICENSE
fair_scoring-0.2.1.dist-info/METADATA
fair_scoring-0.2.1.dist-info/WHEEL
fair_scoring-0.2.1.dist-info/top_level.txt
fair_scoring-0.2.1.dist-info/RECORD
