Metadata-Version: 2.1
Name: fair-scoring
Version: 0.2.1
Summary: Fairness metrics for continuous risk scores
Home-page: https://github.com/schufa-innovationlab/fair-scoring
Author: SCHUFA Holding AG
License: Apache 2.0
Project-URL: Documentation, https://fair-scoring.readthedocs.io/en/stable/
Project-URL: Changelog, https://fair-scoring.readthedocs.io/en/stable/changelog.html
Project-URL: Source code, https://github.com/schufa-innovationlab/fair-scoring
Classifier: License :: OSI Approved :: Apache Software License
Classifier: Programming Language :: Python :: 3 :: Only
Classifier: Programming Language :: Python :: 3.9
Classifier: Programming Language :: Python :: 3.10
Classifier: Programming Language :: Python :: 3.11
Classifier: Programming Language :: Python :: 3.12
Requires-Python: >=3.9
License-File: LICENSE
Requires-Dist: numpy<2.0,>=1.22.0
Requires-Dist: scikit-learn>=1.0.0
Requires-Dist: matplotlib>=3.6.0
Requires-Dist: seaborn>=0.12.0
Provides-Extra: dev
Requires-Dist: sphinx>=6.2.1; extra == "dev"
Requires-Dist: sphinx-book-theme>=1.1.0; extra == "dev"
Requires-Dist: sphinx-autoapi>=3.0.0; extra == "dev"
Requires-Dist: sphinx-design>=0.6.0; extra == "dev"
Requires-Dist: myst-nb>=1.0.0; extra == "dev"
Requires-Dist: pytest>=7.4; extra == "dev"
Requires-Dist: pandas>=2.2.1; extra == "dev"
